{
  "carvers": [
    "minecraft:cave",
    "minecraft:cave_extra_underground",
    "minecraft:canyon"
  ],
  "downfall": 0.0,
  "effects": {
    "fog_color": 16777215,
    "sky_color": 16777215,
    "water_color": 16777215,
    "water_fog_color": 16777215,
    "grass_color": 16777215,
    "foliage_color": 16777215,
    "dry_foliage_color": 16777215,
    "mood_sound": {
      "sound": "minecraft:ambient.cave",
      "tick_delay": 6000,
      "block_search_extent": 8,
      "offset": 2.0
    },
    "music": [
      {
        "data": {
          "sound": "minecraft:music.overworld.forest",
          "min_delay": 12000,
          "max_delay": 24000,
          "replace_current_music": false
        },
        "weight": 1
      }
    ],
    "music_volume": 1.0
  },
  "features": [
    [], [], [], [], [], [], [], [], [], [], []
  ],
  "has_precipitation": false,
  "spawn_costs": {},
  "spawners": {
    "ambient": [],
    "axolotls": [],
    "creature": [],
    "misc": [],
    "monster": [],
    "underground_water_creature": [],
    "water_ambient": [],
    "water_creature": []
  },
  "temperature": 0.00
}
